setup.py
aihttp/__init__.py
aihttp/cli.py
aihttp.egg-info/PKG-INFO
aihttp.egg-info/SOURCES.txt
aihttp.egg-info/dependency_links.txt
aihttp.egg-info/entry_points.txt
aihttp.egg-info/top_level.txt