Metadata-Version: 2.1
Name: aihttp
Version: 0.1
Summary: A harmless package to prevent exploitation
Home-page: UNKNOWN
Author: htdge
Author-email: htdge@protonmail.com
License: UNKNOWN
Platform: UNKNOWN
